fidovault.py
fidovault-0.1.0.dist-info/entry_points.txt
fidovault-0.1.0.dist-info/licenses/COPYING
fidovault-0.1.0.dist-info/WHEEL
fidovault-0.1.0.dist-info/METADATA
fidovault-0.1.0.dist-info/RECORD
