Metadata-Version: 2.4
Name: fidovault
Version: 0.1.0
Summary: Control access to secrets via symmetric encryption and decryption using FIDO2 authenticators.
Author-email: Thomas More <tmore1@gmx.com>
License-Expression: GPL-3.0-or-later
License-File: COPYING
Requires-Dist: cryptography
Requires-Dist: fido2 >=2.0.0
Project-URL: Home, https://github.com/tmo1/fidovault/
